Metadata-Version: 1.0
Name: feris-first-pypi-package
Version: 0.2
Summary: Udacity Gaussian distributions
Home-page: UNKNOWN
Author: UNKNOWN
Author-email: UNKNOWN
License: UNKNOWN
Platform: UNKNOWN
